disvia/__init__.py
disvia/disvia.py
disvia-0.0.2.dist-info/METADATA
disvia-0.0.2.dist-info/WHEEL
disvia-0.0.2.dist-info/top_level.txt
disvia-0.0.2.dist-info/RECORD
